nemati/__init__.py
nemati/_client.py
nemati/_config.py
nemati/_exceptions.py
nemati/_http.py
nemati/_version.py
nemati/_async/__init__.py
nemati/_async/_client.py
nemati/models/__init__.py
nemati/models/account.py
nemati/models/audio.py
nemati/models/chat.py
nemati/models/documents.py
nemati/models/image.py
nemati/models/market.py
nemati/models/trends.py
nemati/models/writer.py
nemati/resources/__init__.py
nemati/resources/account.py
nemati/resources/audio.py
nemati/resources/chat.py
nemati/resources/documents.py
nemati/resources/image.py
nemati/resources/market.py
nemati/resources/trends.py
nemati/resources/writer.py
nemati_ai-0.1.2.dist-info/METADATA
nemati_ai-0.1.2.dist-info/WHEEL
nemati_ai-0.1.2.dist-info/licenses/LICENSE
nemati_ai-0.1.2.dist-info/RECORD
