Metadata-Version: 2.4
Name: nemati-ai
Version: 0.1.2
Summary: Official Python SDK for Nemati AI - AI Content Creation, Image Generation, Trend Discovery & More
Project-URL: Homepage, https://nemati.ai
Project-URL: Documentation, https://docs.nemati.ai/sdk/python
Project-URL: Repository, https://github.com/nemati-ai/nemati
Project-URL: Changelog, https://github.com/nemati-ai/nemati/blob/main/CHANGELOG.md
Project-URL: Issues, https://github.com/nemati-ai/nemati/issues
Author-email: NEMATI AI <support@nemati.ai>
License-Expression: MIT
License-File: LICENSE
Keywords: ai,chatgpt,content-creation,image-generation,nemati,openai,sdk,text-to-speech,trend-discovery
Classifier: Development Status :: 4 - Beta
Classifier: Intended Audience :: Developers
Classifier: License :: OSI Approved :: MIT License
Classifier: Operating System :: OS Independent
Classifier: Programming Language :: Python :: 3
Classifier: Programming Language :: Python :: 3.8
Classifier: Programming Language :: Python :: 3.9
Classifier: Programming Language :: Python :: 3.10
Classifier: Programming Language :: Python :: 3.11
Classifier: Programming Language :: Python :: 3.12
Classifier: Topic :: Scientific/Engineering :: Artificial Intelligence
Classifier: Topic :: Software Development :: Libraries :: Python Modules
Requires-Python: >=3.8
Requires-Dist: httpx>=0.25.0
Requires-Dist: pydantic>=2.0.0
Requires-Dist: typing-extensions>=4.0.0
Provides-Extra: dev
Requires-Dist: black>=23.0.0; extra == 'dev'
Requires-Dist: mypy>=1.0.0; extra == 'dev'
Requires-Dist: pytest-asyncio>=0.21.0; extra == 'dev'
Requires-Dist: pytest-cov>=4.0.0; extra == 'dev'
Requires-Dist: pytest>=7.0.0; extra == 'dev'
Requires-Dist: respx>=0.20.0; extra == 'dev'
Requires-Dist: ruff>=0.1.0; extra == 'dev'
